[
  {
    "id": "fd562836-8804-4d7e-8c8e-515b32da2738",
    "title": "o primeiro",
    "description": "pra ver se tá pegando",
    "completed_at": null,
    "updated_at": "2025-03-30T23:26:07.622Z"
  },
  {
    "id": "e8d87b3a-3c71-4434-9948-d5bbf784ac92",
    "title": "o segundo",
    "description": "pra testar",
    "completed_at": null,
    "updated_at": "2025-03-30T23:26:33.572Z"
  },
  {
    "id": "999771a8-553e-4944-bcf5-45d4ec8ed564",
    "title": "o terceiro",
    "description": "vou completar ele agora",
    "completed_at": "2025-03-30T23:28:24.702Z",
    "updated_at": "2025-03-30T23:28:24.702Z"
  },
  {
    "id": "6077e3a6-be5e-431b-a070-a5d395742dbc",
    "title": "o quarto",
    "description": "pra completar",
    "completed_at": null,
    "updated_at": "2025-03-30T23:28:55.946Z"
  },
  {
    "id": "45f0ea54-b2b1-4bca-b403-cef6c380e54d",
    "title": "o quarto",
    "description": "pra completar",
    "completed_at": null,
    "created_at": "2025-03-31T00:36:13.476Z",
    "updated_at": "2025-03-31T00:36:13.476Z"
  },
  {
    "id": "b6bdb76f-426a-4f4d-a736-0c3ee5d04011",
    "title": "Task 01",
    "description": "Descrição da Task 01",
    "completed_at": null,
    "created_at": "2025-03-31T00:36:48.992Z",
    "updated_at": "2025-03-31T00:36:48.992Z"
  },
  {
    "id": "96744c29-bb32-4ec3-afe3-fcf25363429a",
    "title": "Task 02",
    "description": "Descrição da Task 02",
    "completed_at": null,
    "created_at": "2025-03-31T00:36:49.010Z",
    "updated_at": "2025-03-31T00:36:49.010Z"
  },
  {
    "id": "a4e498bd-4cbc-4b00-9d09-bd6f6c093849",
    "title": "Task 03",
    "description": "Descrição da Task 03",
    "completed_at": null,
    "created_at": "2025-03-31T00:36:49.026Z",
    "updated_at": "2025-03-31T00:36:49.026Z"
  },
  {
    "id": "882283ba-2218-4e78-bbc8-27d9fceff837",
    "title": "Task 04",
    "description": "Descrição da Task 04",
    "completed_at": null,
    "created_at": "2025-03-31T00:36:49.037Z",
    "updated_at": "2025-03-31T00:36:49.037Z"
  },
  {
    "id": "8837986f-8caf-4014-9152-e530dea68721",
    "title": "Task 05",
    "description": "Descrição da Task 05",
    "completed_at": null,
    "created_at": "2025-03-31T00:36:49.050Z",
    "updated_at": "2025-03-31T00:36:49.050Z"
  }
]